<Properties StartupConfiguration="{A1733EAB-8F48-4BB0-A2A3-A898994F1C62}|Default">
  <MonoDevelop.Ide.ItemProperties.Pokedex.BlazorWASM FirstBuild="True" PreferredExecutionTarget="/Applications/Safari.app" />
  <MonoDevelop.Ide.Workbench ActiveDocument="Pokedex.BlazorWASM/Pages/Index.razor">
    <Files>
      <File FileName="Pokedex.BlazorWASM/Models/Pokemon.cs" Line="24" Column="1" />
      <File FileName="Pokedex.BlazorWASM/Pages/Index.razor" Line="1" Column="1" />
    </Files>
    <Pads>
      <Pad Id="ProjectPad">
        <State name="__root__">
          <Node name="Pokedex.BlazorWASM" expanded="True">
            <Node name="Pokedex.BlazorWASM" expanded="True">
              <Node name="Models" expanded="True" />
              <Node name="Pages" expanded="True">
                <Node name="Index.razor" selected="True" />
              </Node>
            </Node>
          </Node>
        </State>
      </Pad>
    </Pads>
  </MonoDevelop.Ide.Workbench>
  <MonoDevelop.Ide.DebuggingService.PinnedWatches />
  <MonoDevelop.Ide.Workspace ActiveConfiguration="Debug" />
  <MonoDevelop.Ide.DebuggingService.Breakpoints>
    <BreakpointStore />
  </MonoDevelop.Ide.DebuggingService.Breakpoints>
  <MultiItemStartupConfigurations />
</Properties>